odoo/addons/ssi_partner_education_level/README.rst
odoo/addons/ssi_partner_education_level/__init__.py
odoo/addons/ssi_partner_education_level/__manifest__.py
odoo/addons/ssi_partner_education_level/menu.xml
odoo/addons/ssi_partner_education_level/models/__init__.py
odoo/addons/ssi_partner_education_level/models/partner_field_of_study.py
odoo/addons/ssi_partner_education_level/models/partner_formal_education_level.py
odoo/addons/ssi_partner_education_level/models/res_partner.py
odoo/addons/ssi_partner_education_level/security/ir.model.access.csv
odoo/addons/ssi_partner_education_level/security/res_group_data.xml
odoo/addons/ssi_partner_education_level/static/description/icon.png
odoo/addons/ssi_partner_education_level/views/partner_field_of_study_views.xml
odoo/addons/ssi_partner_education_level/views/partner_formal_education_level_views.xml
odoo/addons/ssi_partner_education_level/views/res_partner_view.xml
odoo14_addon_ssi_partner_education_level-14.0.1.2.0.dist-info/METADATA
odoo14_addon_ssi_partner_education_level-14.0.1.2.0.dist-info/WHEEL
odoo14_addon_ssi_partner_education_level-14.0.1.2.0.dist-info/top_level.txt
odoo14_addon_ssi_partner_education_level-14.0.1.2.0.dist-info/RECORD
